lakefs_spec/__init__.py
lakefs_spec/errors.py
lakefs_spec/py.typed
lakefs_spec/spec.py
lakefs_spec/transaction.py
lakefs_spec/types.py
lakefs_spec/util.py
lakefs_spec-0.13.0.dist-info/licenses/LICENSE
lakefs_spec-0.13.0.dist-info/METADATA
lakefs_spec-0.13.0.dist-info/WHEEL
lakefs_spec-0.13.0.dist-info/top_level.txt
lakefs_spec-0.13.0.dist-info/RECORD
