Metadata-Version: 2.4
Name: lakefs-spec
Version: 0.13.0
Summary: An fsspec implementation for lakeFS.
Author-email: appliedAI Institute for Europe <lakefs-spec@appliedai-institute.de>
Maintainer-email: Nicholas Junge <n.junge@appliedai-institute.de>, Max Mynter <m.mynter@appliedai-institute.de>, Adrian Rumpold <a.rumpold@appliedai-institute.de>
License: Apache-2.0
Project-URL: Homepage, https://github.com/aai-institute/lakefs-spec
Project-URL: Repository, https://github.com/aai-institute/lakefs-spec.git
Project-URL: Issues, https://github.com/aai-institute/lakefs-spec/issues
Project-URL: Discussions, https://github.com/aai-institute/lakefs-spec/discussions
Project-URL: Documentation, https://lakefs-spec.org/latest
Keywords: lakeFS,fsspec
Classifier: Development Status :: 4 - Beta
Classifier: Intended Audience :: Developers
Classifier: Intended Audience :: Science/Research
Classifier: License :: OSI Approved :: Apache Software License
Classifier: Operating System :: OS Independent
Classifier: Programming Language :: Python :: 3
Classifier: Topic :: Scientific/Engineering
Classifier: Topic :: Scientific/Engineering :: Artificial Intelligence
Classifier: Topic :: Scientific/Engineering :: Information Analysis
Classifier: Topic :: Software Development :: Libraries :: Python Modules
Classifier: Topic :: Software Development :: Version Control
Classifier: Topic :: System :: Filesystems
Classifier: Topic :: Utilities
Classifier: Typing :: Typed
Requires-Python: >=3.10
License-File: LICENSE
Requires-Dist: fsspec>=2023.12.0
Requires-Dist: lakefs>=0.2.0
Dynamic: license-file
